{
  "project_info": {
    "project_number": "408502757978",
    "firebase_url": "https://don-t-sleep.firebaseio.com",
    "project_id": "don-t-sleep",
    "storage_bucket": "don-t-sleep.firebasestorage.app"
  },
  "client": [
    {
      "client_info": {
        "mobilesdk_app_id": "1:408502757978:android:789410de71ecd791ba4663",
        "android_client_info": {
          "package_name": "com.ilieinc.dontsleep"
        }
      },
      "oauth_client": [],
      "api_key": [
        {
          "current_key": "AIzaSyAc8r7dp8nKWkIUP-1hi4wFYMUMcBlFEqM"
        }
      ],
      "services": {
        "appinvite_service": {
          "other_platform_oauth_client": []
        }
      }
    },
    {
      "client_info": {
        "mobilesdk_app_id": "1:408502757978:android:b80c7be32c3332adba4663",
        "android_client_info": {
          "package_name": "com.ilieinc.dontsleep.test"
        }
      },
      "oauth_client": [],
      "api_key": [
        {
          "current_key": "AIzaSyAc8r7dp8nKWkIUP-1hi4wFYMUMcBlFEqM"
        }
      ],
      "services": {
        "appinvite_service": {
          "other_platform_oauth_client": []
        }
      }
    }
  ],
  "configuration_version": "1"
}